aimms/__init__.py
aimms/model/__init__.py
aimms/model/declaration_section.py
aimms/model/enums/__init__.py
aimms/model/enums/args_enum.py
aimms/model/enums/attribute_values.py
aimms/model/enums/data_return_types.py
aimms/model/enums/identifier_flags.py
aimms/model/enums/me_attribute_types.py
aimms/model/enums/me_identifier_types.py
aimms/model/enums/storage_types.py
aimms/model/identifiers/__init__.py
aimms/model/identifiers/constraint.py
aimms/model/identifiers/data_identifiers.py
aimms/model/identifiers/identifier.py
aimms/model/identifiers/index.py
aimms/model/identifiers/mathematical_program.py
aimms/model/identifiers/parameter.py
aimms/model/identifiers/set.py
aimms/model/identifiers/utils.py
aimms/model/identifiers/variable.py
aimms/model/library.py
aimms/model/module.py
aimms/model/procedure.py
aimms/project/__init__.py
aimms/project/project.py
aimms/utils.py
aimms_api_py.cp313-win_amd64.pyd
aimms_api_py-1.0.1.post13.dist-info/METADATA
aimms_api_py-1.0.1.post13.dist-info/WHEEL
aimms_api_py-1.0.1.post13.dist-info/RECORD
